thonnycontrib/ai_helper/__init__.py
thonnycontrib/ai_helper/ai_helper.py
thonny_ai_helper-0.1.3.dist-info/METADATA
thonny_ai_helper-0.1.3.dist-info/WHEEL
thonny_ai_helper-0.1.3.dist-info/top_level.txt
thonny_ai_helper-0.1.3.dist-info/RECORD
