Metadata-Version: 2.4
Name: thonny-ai-helper
Version: 0.1.3
Summary: An AI Assistant plugin for the Thonny Python IDE.
Author-email: pondahai <dahai.pon@gmail.com>
Maintainer-email: pondahai <dahai.pon@gmail.com>
License: MIT
Project-URL: Homepage, https://github.com/pondahai/thonny_ai_helper
Project-URL: Repository, https://github.com/pondahai/thonny_ai_helper
Keywords: thonny,plugin,ai,assistant,llm,openai
Classifier: Development Status :: 3 - Alpha
Classifier: Environment :: Plugins
Classifier: Intended Audience :: Developers
Classifier: Intended Audience :: Education
Classifier: License :: OSI Approved :: MIT License
Classifier: Natural Language :: English
Classifier: Operating System :: OS Independent
Classifier: Programming Language :: Python :: 3
Classifier: Programming Language :: Python :: 3.8
Classifier: Programming Language :: Python :: 3.9
Classifier: Programming Language :: Python :: 3.10
Classifier: Programming Language :: Python :: 3.11
Classifier: Programming Language :: Python :: 3.12
Classifier: Topic :: Education
Classifier: Topic :: Software Development :: Debuggers
Classifier: Topic :: Text Editors :: Integrated Development Environments (IDE)
Requires-Python: >=3.8
Requires-Dist: requests>=2.20.0
Requires-Dist: markdown-it-py>=3.0.0
